luana_santos_csv_converter/__init__.py
luana_santos_csv_converter/converter.py
luana_santos_csv_converter/converterj.py
luana_santos_csv_converter-0.1.0.dist-info/entry_points.txt
luana_santos_csv_converter-0.1.0.dist-info/WHEEL
luana_santos_csv_converter-0.1.0.dist-info/METADATA
luana_santos_csv_converter-0.1.0.dist-info/RECORD
