Metadata-Version: 2.1
Name: luana-santos-csv-converter
Version: 0.1.0
Summary: Convert csv to json and vice versa. For learning purposes.
Author: Luana Santos
Author-email: luanasilvia.lss@gmail.com
Requires-Python: >=3.9,<4.0
Classifier: Programming Language :: Python :: 3
Classifier: Programming Language :: Python :: 3.10
Classifier: Programming Language :: Python :: 3.9
Requires-Dist: click (>=8.0.3,<9.0.0)
Requires-Dist: pandas (>=1.3.5,<2.0.0)
